typesense_server_wrapper_omega/__init__.py
typesense_server_wrapper_omega/typesense-server.2.bin
typesense_server_wrapper_omega-0.24.1.dist-info/LICENSE
typesense_server_wrapper_omega-0.24.1.dist-info/METADATA
typesense_server_wrapper_omega-0.24.1.dist-info/WHEEL
typesense_server_wrapper_omega-0.24.1.dist-info/top_level.txt
typesense_server_wrapper_omega-0.24.1.dist-info/RECORD
